py3plex/__init__.py
py3plex/__main__.py
py3plex/_parallel.py
py3plex/cli.py
py3plex/config.py
py3plex/dsl_legacy.py
py3plex/errors.py
py3plex/exceptions.py
py3plex/fast_examples.py
py3plex/graph_ops.py
py3plex/linter.py
py3plex/logging_config.py
py3plex/pipeline.py
py3plex/profiling.py
py3plex/requirements.py
py3plex/temporal_utils.py
py3plex/temporal_utils_extended.py
py3plex/temporal_view.py
py3plex/utils.py
py3plex/validation.py
py3plex/workflows.py
py3plex/algebra/__init__.py
py3plex/algebra/backend.py
py3plex/algebra/closure.py
py3plex/algebra/fixed_point.py
py3plex/algebra/lift.py
py3plex/algebra/paths.py
py3plex/algebra/registry.py
py3plex/algebra/semiring.py
py3plex/algebra/witness.py
py3plex/algorithms/__init__.py
py3plex/algorithms/advanced_random_generators.py
py3plex/algorithms/attribute_correlation.py
py3plex/algorithms/centrality_toolkit.py
py3plex/algorithms/community_comparison.py
py3plex/algorithms/graph_summarization.py
py3plex/algorithms/layer_similarity.py
py3plex/algorithms/meta_flow_report.py
py3plex/algorithms/multicentrality.py
py3plex/algorithms/multilayer_clustering.py
py3plex/algorithms/requirements_registry.py
py3plex/algorithms/robustness_testing.py
py3plex/algorithms/sir_multiplex.py
py3plex/algorithms/statistical_report.py
py3plex/algorithms/centrality/__init__.py
py3plex/algorithms/centrality/approx_betweenness.py
py3plex/algorithms/centrality/approx_closeness.py
py3plex/algorithms/centrality/approx_pagerank.py
py3plex/algorithms/centrality/explain.py
py3plex/algorithms/community_detection/NoRC.py
py3plex/algorithms/community_detection/__init__.py
py3plex/algorithms/community_detection/auto_select.py
py3plex/algorithms/community_detection/autocommunity.py
py3plex/algorithms/community_detection/autocommunity_executor.py
py3plex/algorithms/community_detection/budget.py
py3plex/algorithms/community_detection/community_louvain.py
py3plex/algorithms/community_detection/community_measures.py
py3plex-1.1.3.dist-info/licenses/LICENSE
py3plex-1.1.3.dist-info/METADATA
py3plex-1.1.3.dist-info/WHEEL
py3plex-1.1.3.dist-info/entry_points.txt
py3plex-1.1.3.dist-info/top_level.txt
py3plex-1.1.3.dist-info/RECORD
