Metadata-Version: 2.4
Name: py3plex
Version: 1.1.3
Summary: A Multilayer network analysis python3 library
Author-email: Blaž Škrlj <blaz.skrlj@ijs.si>
License: MIT
Project-URL: Homepage, https://github.com/SkBlaz/py3plex
Project-URL: Documentation, https://skblaz.github.io/py3plex/
Project-URL: Repository, https://github.com/SkBlaz/py3plex
Project-URL: Bug Tracker, https://github.com/SkBlaz/py3plex/issues
Keywords: network analysis,multilayer networks,heterogeneous networks,graph visualization,network science
Classifier: Development Status :: 4 - Beta
Classifier: Intended Audience :: Science/Research
Classifier: License :: OSI Approved :: MIT License
Classifier: Programming Language :: Python :: 3
Classifier: Programming Language :: Python :: 3.8
Classifier: Programming Language :: Python :: 3.9
Classifier: Programming Language :: Python :: 3.10
Classifier: Programming Language :: Python :: 3.11
Classifier: Programming Language :: Python :: 3.12
Classifier: Topic :: Scientific/Engineering :: Information Analysis
Classifier: Topic :: Scientific/Engineering :: Visualization
Requires-Python: >=3.8
License-File: LICENSE
Requires-Dist: numpy>=1.19.0
Requires-Dist: rdflib>=6.0.0
Requires-Dist: scipy>=1.5.0
Requires-Dist: networkx>=2.5
Requires-Dist: cython>=0.29.0
Requires-Dist: tqdm>=4.40.0
Requires-Dist: matplotlib>=3.3.0
Requires-Dist: gensim>=4.0.0
Requires-Dist: scikit-learn>=0.24.0
Requires-Dist: bitarray>=2.0.0
Requires-Dist: seaborn>=0.11.0
Provides-Extra: dev
Requires-Dist: pytest>=7.0; extra == "dev"
Requires-Dist: pytest-timeout>=2.1; extra == "dev"
Requires-Dist: pytest-cov>=4.0; extra == "dev"
Requires-Dist: pytest-benchmark<5.0,>=4.0; extra == "dev"
Requires-Dist: black>=23.0; extra == "dev"
Requires-Dist: ruff>=0.1.0; extra == "dev"
Requires-Dist: mypy>=1.0; extra == "dev"
Requires-Dist: types-six>=1.16.0; extra == "dev"
Requires-Dist: pre-commit>=3.0; extra == "dev"
Requires-Dist: crosshair-tool>=0.0.60; extra == "dev"
Requires-Dist: icontract>=2.6.0; extra == "dev"
Requires-Dist: z3-solver>=4.12.0; extra == "dev"
Requires-Dist: hypothesis>=6.0; extra == "dev"
Provides-Extra: tests
Requires-Dist: pytest>=7.0; extra == "tests"
Requires-Dist: pytest-timeout>=2.1; extra == "tests"
Requires-Dist: pytest-cov>=4.0; extra == "tests"
Requires-Dist: hypothesis>=6.0; extra == "tests"
Requires-Dist: hypothesis-networkx>=0.2.0; extra == "tests"
Requires-Dist: networkx>=2.5; extra == "tests"
Requires-Dist: numpy>=1.19.0; extra == "tests"
Requires-Dist: scipy>=1.5.0; extra == "tests"
Requires-Dist: python-louvain>=0.16; extra == "tests"
Provides-Extra: infomap
Requires-Dist: infomap>=2.0.0; extra == "infomap"
Provides-Extra: algos
Requires-Dist: python-louvain>=0.16; extra == "algos"
Requires-Dist: cdlib>=0.3.0; extra == "algos"
Provides-Extra: viz
Requires-Dist: plotly>=5.0.0; extra == "viz"
Requires-Dist: python-igraph>=0.10.0; extra == "viz"
Provides-Extra: workflows
Requires-Dist: pyyaml>=5.1; extra == "workflows"
Provides-Extra: arrow
Requires-Dist: pyarrow>=10.0.0; extra == "arrow"
Provides-Extra: compat
Requires-Dist: networkx>=2.5; extra == "compat"
Requires-Dist: scipy>=1.5.0; extra == "compat"
Requires-Dist: pandas>=1.2.0; extra == "compat"
Requires-Dist: pyarrow>=10.0.0; extra == "compat"
Provides-Extra: igraph
Requires-Dist: python-igraph>=0.10.0; extra == "igraph"
Provides-Extra: pyg
Requires-Dist: torch>=1.10.0; extra == "pyg"
Requires-Dist: torch-geometric>=2.0.0; extra == "pyg"
Provides-Extra: dgl-compat
Requires-Dist: dgl>=0.9.0; extra == "dgl-compat"
Provides-Extra: mcp
Requires-Dist: mcp>=0.9.0; python_version >= "3.10" and extra == "mcp"
Dynamic: license-file
